<?xml version="1.0" encoding="UTF-8"?>
<!DOCTYPE struts-config PUBLIC "-//Apache Software Foundation//DTD Struts Configuration 1.1//EN" "http://jakarta.apache.org/struts/dtds/struts-config_1_1.dtd">
<struts-config>

	<form-beans>
		<form-bean name="ExibirCanaisAtendimentoCaerActionForm"
			type="gcom.gui.portal.caer.ExibirCanaisAtendimentoCaerActionForm" />
	</form-beans>

	<!--******************* PÃGINAS GLOBAIS *******************-->
	<global-forwards />
	<action-mappings>

		<action name="ExibirCanaisAtendimentoCaerActionForm"
			type="gcom.gui.portal.caer.ExibirCanaisAtendimentoCaerAction"
			validate="false" scope="session"
			path="/exibirCanaisAtendimentoCaerAction">			
			<forward name="exibirTeleAtendimentoCaerAction"
				path="/jsp/portal/caer/portal_caer_teleatendimento.jsp" />		
				
			<forward name="exibirOuvidoriaCaerAction"
				path="/jsp/portal/caer/ouvidoria_portal_caer.jsp" />		
				
			
		</action>
	</action-mappings>

	<message-resources null="false"
		parameter="gcom.properties.application" />
</struts-config>

